tumbo/__init__.py
tumbo/__main__.py
tumbo/cli.py
tumbo/tumbo.py
tumbo/utils.py
tumbo-0.7.dist-info/LICENSE
tumbo-0.7.dist-info/METADATA
tumbo-0.7.dist-info/WHEEL
tumbo-0.7.dist-info/entry_points.txt
tumbo-0.7.dist-info/top_level.txt
tumbo-0.7.dist-info/RECORD
