Metadata-Version: 2.1
Name: tumbo
Version: 0.7
Summary: Matrix builder for docker
Home-page: https://github.com/cupcakearmy/tumbo
Author: cupcakearmy
Author-email: hi@nicco.io
License: GPLv3
Platform: UNKNOWN
Classifier: Programming Language :: Python :: 3
Classifier: License :: OSI Approved :: GNU General Public License v3 (GPLv3)
Classifier: Operating System :: OS Independent
Requires-Python: >=3.6
Requires-Dist: Jinja2 (==2.10.3)
Requires-Dist: PyYAML (==5.2)
Requires-Dist: termcolor (==1.1.0)
